LICENSE
MANIFEST.in
README.md
prism-api-version.txt
setup.py
org/polypheny/prism/connection_requests_pb2.py
org/polypheny/prism/connection_responses_pb2.py
org/polypheny/prism/document_frame_pb2.py
org/polypheny/prism/error_pb2.py
org/polypheny/prism/graph_frame_pb2.py
org/polypheny/prism/meta_requests_pb2.py
org/polypheny/prism/meta_responses_pb2.py
org/polypheny/prism/namespace_meta_requests_pb2.py
org/polypheny/prism/namespace_meta_responses_pb2.py
org/polypheny/prism/protointerface_pb2.py
org/polypheny/prism/relational_frame_pb2.py
org/polypheny/prism/statement_requests_pb2.py
org/polypheny/prism/statement_responses_pb2.py
org/polypheny/prism/transaction_requests_pb2.py
org/polypheny/prism/transaction_responses_pb2.py
org/polypheny/prism/value_pb2.py
org/polypheny/prism/version.py
polypheny_prism_api.egg-info/PKG-INFO
polypheny_prism_api.egg-info/SOURCES.txt
polypheny_prism_api.egg-info/dependency_links.txt
polypheny_prism_api.egg-info/requires.txt
polypheny_prism_api.egg-info/top_level.txt