Metadata-Version: 2.1
Name: polypheny-prism-api
Version: 1.9
Summary: Polypheny Prism API files for Python
Home-page: https://polypheny.com/
Author: The Polypheny Project
Author-email: mail@polypheny.org
License: Apache License, Version 2.0
Project-URL: Documentation, https://docs.polypheny.com/en/latest/query_interfaces/prism/protocol
Project-URL: Code, https://github.com/polypheny/Polypheny-Prism-API
Platform: UNKNOWN
